[
  {
    "href": "https://www.amazon.co.jp/deal/5f4da7bc?ref=dlx_deals_gd_dcl_img_0_5f4da7bc_dt_sl15_7f&tag=tokkajohotsu-22",
    "date": "2022-11-18-0229",
    "asin": null,
    "price": null,
    "aside_price": null,
    "image": "https://m.media-amazon.com/images/I/411UfFQBnYL._AC_UF226,226_FMjpg_.jpg",
    "label": "【本日限定】防寒グッズ 電熱ベストがお買い得; ",
    "textContent": "最大52%OFF特選タイムセール最大52%OFF特選タイムセール【本日限定】防寒グッズ 電熱ベストがお買い得"
  },
  {
    "href": "https://www.amazon.co.jp/deal/2df58a4e?ref=dlx_deals_gd_dcl_img_1_2df58a4e_dt_sl15_7f&tag=tokkajohotsu-22",
    "date": "2022-11-18-0229",
    "asin": null,
    "price": null,
    "aside_price": null,
    "image": "https://m.media-amazon.com/images/I/4108Rf7-L5L._AC_UF226,226_FMjpg_.jpg",
    "label": "【本日限定】モバイルバッテリーと加湿器がお買い得; ",
    "textContent": "最大22%OFF特選タイムセール最大22%OFF特選タイムセール【本日限定】モバイルバッテリーと加湿器がお買い得"
  },
  {
    "href": "https://www.amazon.co.jp/deal/d70ea3c3?ref=dlx_deals_gd_dcl_img_2_d70ea3c3_dt_sl15_7f&tag=tokkajohotsu-22",
    "date": "2022-11-18-0229",
    "asin": null,
    "price": null,
    "aside_price": null,
    "image": "https://m.media-amazon.com/images/I/41U7aZPKi5L._AC_UF226,226_FMjpg_.jpg",
    "label": "【本日限定】スマートウォッチとタッチペンがお買い得; ",
    "textContent": "最大62%OFF特選タイムセール最大62%OFF特選タイムセール【本日限定】スマートウォッチとタッチペンがお買い得"
  },
  {
    "href": "https://www.amazon.co.jp/deal/4a24b9b6?searchAlias=fashion&ref=dlx_deals_gd_dcl_img_3_4a24b9b6_dt_sl15_7f&tag=tokkajohotsu-22",
    "date": "2022-11-18-0229",
    "asin": null,
    "price": null,
    "aside_price": null,
    "image": "https://m.media-amazon.com/images/I/31ttMt3bWuL._AC_UF226,226_FMjpg_.jpg",
    "label": "［Amazonブランド］レディースウェアがお買い得; ",
    "textContent": "最大24%OFF特選タイムセール最大24%OFF特選タイムセール［Amazonブランド］レディースウェアがお買い得"
  },
  {
    "href": "https://www.amazon.co.jp/deal/ba6cfa64?searchAlias=fashion&ref=dlx_deals_gd_dcl_img_4_ba6cfa64_dt_sl15_7f&tag=tokkajohotsu-22",
    "date": "2022-11-18-0229",
    "asin": null,
    "price": null,
    "aside_price": null,
    "image": "https://m.media-amazon.com/images/I/41Ny2CK76-L._AC_UF226,226_FMjpg_.jpg",
    "label": "クラークスのシューズがお買い得; ",
    "textContent": "最大50%OFF特選タイムセール最大50%OFF特選タイムセールクラークスのシューズがお買い得"
  },
  {
    "href": "https://www.amazon.co.jp/deal/a2e13536?searchAlias=fashion&ref=dlx_deals_gd_dcl_img_5_a2e13536_dt_sl15_7f&tag=tokkajohotsu-22",
    "date": "2022-11-18-0229",
    "asin": null,
    "price": null,
    "aside_price": null,
    "image": "https://m.media-amazon.com/images/I/31outQXD8ML._AC_UF226,226_FMjpg_.jpg",
    "label": "リゲッタカヌーのシューズがお買い得; ",
    "textContent": "最大45%OFF特選タイムセール最大45%OFF特選タイムセールリゲッタカヌーのシューズがお買い得"
  },
  {
    "href": "https://www.amazon.co.jp/dp/B0B8CV52YL?ref=dlx_deals_gd_dcl_img_6_7ecd9884_dt_sl15_7f&tag=tokkajohotsu-22",
    "date": "2022-11-18-0229",
    "asin": "B0B8CV52YL",
    "price": null,
    "aside_price": null,
    "image": "https://m.media-amazon.com/images/I/51D+sYBLSCL._AC_UF226,226_FMjpg_.jpg",
    "label": "Fire TV StickとEcho Dot 第4世代時計付きのまとめ買いがお買い得; ",
    "textContent": "セールセールFire TV StickとEcho Dot 第4世代時計付きのまとめ買いがお買い得"
  },
  {
    "href": "https://www.amazon.co.jp/b/?node=10469809051&ref=dlx_deals_gd_dcl_img_7_739aa4b8_dt_sl15_7f&tag=tokkajohotsu-22",
    "date": "2022-11-18-0229",
    "asin": null,
    "price": null,
    "aside_price": null,
    "image": "https://m.media-amazon.com/images/I/41An8pxMXoL._AC_UF226,226_FMjpg_.jpg",
    "label": "Fireタブレットがお買い得; ",
    "textContent": "セールセールFireタブレットがお買い得"
  },
  {
    "href": "https://www.amazon.co.jp/dp/B0B385WJWD/?ref=dlx_deals_gd_dcl_img_8_1de540e3_dt_sl15_7f&tag=tokkajohotsu-22",
    "date": "2022-11-18-0229",
    "asin": "B0B385WJWD",
    "price": null,
    "aside_price": null,
    "image": "https://m.media-amazon.com/images/I/31FF67xQ5qL._AC_UF226,226_FMjpg_.jpg",
    "label": "【セットで20%オフ】Ring 屋内外カメラ2台 予備バッテリー; ",
    "textContent": "セールセール【セットで20%オフ】Ring 屋内外カメラ2台 予備バッテリー"
  },
  {
    "href": "https://www.amazon.co.jp/dp/B09DN2BH3Q?ref=dlx_deals_gd_dcl_img_9_75548ace_dt_sl15_7f&tag=tokkajohotsu-22",
    "date": "2022-11-18-0229",
    "asin": "B09DN2BH3Q",
    "price": null,
    "aside_price": null,
    "image": "https://m.media-amazon.com/images/I/317oHxv+zxL._AC_UF226,226_FMjpg_.jpg",
    "label": "【セット買い】 Kindle Paperwhite、カバー、保護フィルム; ",
    "textContent": "セールセール【セット買い】 Kindle Paperwhite、カバー、保護フィルム"
  },
  {
    "href": "https://www.amazon.co.jp/%E3%83%AF%E3%82%A4%E3%83%A4%E3%83%AC%E3%82%B9%E3%82%A4%E3%83%A4%E3%83%9B%E3%83%B3-Bluetooth-%E3%82%A4%E3%83%A4%E3%83%9B%E3%83%B3-%E5%B7%A6%E5%8F%B3%E5%88%86%E9%9B%A2%E5%9E%8B-WS-28-003/dp/B0B8SB9KQ1?ref=dlx_deals_gd_dcl_img_10_2dbae8db_dt_sl15_7f&tag=tokkajohotsu-22",
    "date": "2022-11-18-0229",
    "asin": "B0B8SB9KQ1",
    "price": null,
    "aside_price": null,
    "image": "https://m.media-amazon.com/images/I/41bmCUmh3NL._AC_UF226,226_FMjpg_.jpg",
    "label": "ワイヤレスイヤホン Bluetooth イヤホン 片耳/両耳 左右分離型 音量調整 小型/軽量; ",
    "textContent": "￥50,999以下セール￥50,999以下セールワイヤレスイヤホン Bluetooth イヤホン 片耳/両耳 左右分離型 音量調整 小型/軽量"
  },
  {
    "href": "https://www.amazon.co.jp/Skytop-Sktop-%E5%8F%8C%E7%9C%BC%E9%8F%A1/dp/B0BJSZ73W7?ref=dlx_deals_gd_dcl_img_11_7e78899e_dt_sl15_7f&tag=tokkajohotsu-22",
    "date": "2022-11-18-0229",
    "asin": "B0BJSZ73W7",
    "price": null,
    "aside_price": null,
    "image": "https://m.media-amazon.com/images/I/41EAAabepSL._AC_UF226,226_FMjpg_.jpg",
    "label": "Sktop 双眼鏡; ",
    "textContent": "￥50,999以下セール￥50,999以下セールSktop 双眼鏡"
  },
  {
    "href": "https://www.amazon.co.jp/%E3%83%AF%E3%82%A4%E3%83%A4%E3%83%AC%E3%82%B9%E3%82%A4%E3%83%A4%E3%83%9B%E3%83%B3-Bluetooth-LED%E3%83%87%E3%82%A3%E3%82%B9%E3%83%97%E3%83%AC%E3%82%A4%E9%9B%BB%E9%87%8F%E8%A1%A8%E7%A4%BA-AAC%E5%AF%BE%E5%BF%9C-Siri%E5%AF%BE%E5%BF%9C/dp/B0B7K9RXKS?ref=dlx_deals_gd_dcl_img_12_b2b4ee53_dt_sl15_7f&tag=tokkajohotsu-22",
    "date": "2022-11-18-0229",
    "asin": "B0B7K9RXKS",
    "price": null,
    "aside_price": null,
    "image": "https://m.media-amazon.com/images/I/41NRU5bAAOL._AC_UF226,226_FMjpg_.jpg",
    "label": "Bluetooth イヤホン 完全ワイヤレス イヤホン 長時間連続再生 AppleとAndroidデバイスに対応 技適認証済; ",
    "textContent": "￥14,449以下セール￥14,449以下セールBluetooth イヤホン 完全ワイヤレス イヤホン 長時間連続再生 AppleとAndroidデバイスに対応 技適認証済"
  },
  {
    "href": "https://www.amazon.co.jp/%E3%83%AF%E3%82%A4%E3%83%A4%E3%83%AC%E3%82%B9-%E3%82%A4%E3%83%A4%E3%83%9B%E3%83%B3-Bluetooth%E3%82%A4%E3%83%A4%E3%83%9B%E3%83%B3-%E9%9F%B3%E9%87%8F%E8%AA%BF%E6%95%B4%E5%8F%AF%E8%83%BD-Bvf-Q104/dp/B0B6N8BTMC?ref=dlx_deals_gd_dcl_img_13_c67456d1_dt_sl15_7f&tag=tokkajohotsu-22",
    "date": "2022-11-18-0229",
    "asin": "B0B6N8BTMC",
    "price": null,
    "aside_price": null,
    "image": "https://m.media-amazon.com/images/I/31KoQ8m393L._AC_UF226,226_FMjpg_.jpg",
    "label": "骨伝導イヤホン Bluetooth イヤホン; ",
    "textContent": "￥19,999以下セール￥19,999以下セール骨伝導イヤホン Bluetooth イヤホン"
  },
  {
    "href": "https://www.amazon.co.jp/%EF%BC%BA%EF%BC%A3%EF%BC%A7%EF%BC%A5%EF%BC%B2%EF%BC%B5%EF%BC%A9%EF%BC%AA-%E3%82%B7%E3%83%A7%E3%83%AB%E3%83%80%E3%83%BC%E3%83%90%E3%83%83%E3%82%B0-%E3%83%9C%E3%83%87%E3%82%A3%E3%83%BC%E3%83%90%E3%83%83%E3%82%B0-%E3%83%AF%E3%83%B3%E3%82%B7%E3%83%A7%E3%83%AB%E3%83%80%E3%83%BC-%E3%83%AF%E3%83%B3%E3%82%B7%E3%83%A7%E3%83%AB%E3%83%80%E3%83%BC%E3%83%90%E3%83%83%E3%82%B0/dp/B0BC522F4M?ref=dlx_deals_gd_dcl_img_14_153ee971_dt_sl15_7f&tag=tokkajohotsu-22",
    "date": "2022-11-18-0229",
    "asin": "B0BC522F4M",
    "price": null,
    "aside_price": null,
    "image": "https://m.media-amazon.com/images/I/31UltGHR+1L._AC_UF226,226_FMjpg_.jpg",
    "label": "斜め掛け ボディバッグ ショルダーバッグ ボディーバッグ ワンショルダー[zyjb-1]; ",
    "textContent": "最大76%OFFセール最大76%OFFセール斜め掛け ボディバッグ ショルダーバッグ ボディーバッグ ワンショルダー[zyjb-1]"
  },
  {
    "href": "https://www.amazon.co.jp/%E7%9C%9F%E7%A9%BA%E3%83%91%E3%83%83%E3%82%AF%E6%A9%9F-%E7%9C%9F%E7%A9%BA%E3%83%91%E3%83%83%E3%82%AF%E5%99%A8-60Kpa-%E5%90%B8%E5%BC%95%E5%8A%9B60Kpa%E8%84%B1%E6%B0%97%E5%AF%86%E5%B0%81-%E6%97%A5%E6%9C%AC%E8%AA%9E%E8%AA%AC%E6%98%8E%E6%9B%B8%E4%BB%98%E3%81%8D/dp/B0BHSR25SW?ref=dlx_deals_gd_dcl_img_15_77a79970_dt_sl15_7f&tag=tokkajohotsu-22",
    "date": "2022-11-18-0229",
    "asin": "B0BHSR25SW",
    "price": null,
    "aside_price": null,
    "image": "https://m.media-amazon.com/images/I/51mtOZt1MsL._AC_UF226,226_FMjpg_.jpg",
    "label": "真空パック機 真空パック器 自動真空シーラー 真空シール コンパクト ワンタッチ 乾・柔・湿 小型軽量 分離 吸引力60Kpa脱気密封 鮮度長持ち 簡単操作 食品保存 多機能 専用袋10枚 家庭用/業務用 日本語説明書付き; ",
    "textContent": "￥33,999以下セール￥33,999以下セール真空パック機 真空パック器 自動真空シーラー 真空シール コンパクト ワンタッチ 乾・柔・湿 小型軽量 分離 吸引力60Kpa脱気密封 鮮度長持ち 簡単操作 食品保存 多機能 専用袋10枚 家庭用/業務用 日本語説明書付き"
  },
  {
    "href": "https://www.amazon.co.jp/Aeetit-%E3%83%88%E3%83%BC%E3%83%81%E3%83%90%E3%83%BC%E3%83%8A%E3%83%BC-%E5%B1%8B%E5%86%85%E3%81%A8%E3%82%A2%E3%82%A6%E3%83%88%E3%83%89%E3%82%A2-%E3%82%AD%E3%83%A3%E3%83%B3%E3%83%97-%E3%82%AF%E3%83%83%E3%82%AD%E3%83%B3%E3%82%B0%E7%94%A8%E3%83%90%E3%83%BC%E3%83%8A%E3%83%BC/dp/B0B1YTCXRG?ref=dlx_deals_gd_dcl_img_16_aa4ad423_dt_sl15_7f&tag=tokkajohotsu-22",
    "date": "2022-11-18-0229",
    "asin": "B0B1YTCXRG",
    "price": null,
    "aside_price": null,
    "image": "https://m.media-amazon.com/images/I/51BmwcMN20L._AC_UF226,226_FMjpg_.jpg",
    "label": "Aeetit トーチバーナー 屋内とアウトドア キャンプ BBQ クッキング用バーナー; ",
    "textContent": "￥25,499以下セール￥25,499以下セールAeetit トーチバーナー 屋内とアウトドア キャンプ BBQ クッキング用バーナー"
  },
  {
    "href": "https://www.amazon.co.jp/Bluetooth-%E5%AE%8C%E5%85%A8%E3%83%AF%E3%82%A4%E3%83%A4%E3%83%AC%E3%82%B9-%E7%84%A1%E7%B7%9A%E3%82%A4%E3%83%A4%E3%83%9B%E3%83%B3-%E5%B7%A6%E5%8F%B3%E5%88%86%E9%9B%A2%E5%9E%8B-%E6%8A%80%E9%81%A9%E8%AA%8D%E8%A8%BC%E6%B8%88/dp/B0BHQ5FW64?ref=dlx_deals_gd_dcl_img_17_d12f6b8f_dt_sl15_7f&tag=tokkajohotsu-22",
    "date": "2022-11-18-0229",
    "asin": "B0BHQ5FW64",
    "price": null,
    "aside_price": null,
    "image": "https://m.media-amazon.com/images/I/41o8-GEZz7L._AC_UF226,226_FMjpg_.jpg",
    "label": "Bluetooth イヤホン 完全ワイヤレス イヤホン 片耳/両耳 左右分離型; ",
    "textContent": "￥14,109以下セール￥14,109以下セールBluetooth イヤホン 完全ワイヤレス イヤホン 片耳/両耳 左右分離型"
  },
  {
    "href": "https://www.amazon.co.jp/%E3%82%B9%E3%83%9E%E3%83%BC%E3%83%88%E3%82%A6%E3%82%A9%E3%83%83%E3%83%81-%E3%80%901-7%E3%82%A4%E3%83%B3%E3%83%81%E5%A4%A7%E7%94%BB%E9%9D%A2%E3%80%91-Bluetooth-%E3%82%B9%E3%83%9D%E3%83%BC%E3%83%84%E3%82%A6%E3%82%A9%E3%83%83%E3%83%81-Android%E5%AF%BE%E5%BF%9C/dp/B0BCVB1GFN?ref=dlx_deals_gd_dcl_img_18_c3f87cfd_dt_sl15_7f&tag=tokkajohotsu-22",
    "date": "2022-11-18-0229",
    "asin": "B0BCVB1GFN",
    "price": null,
    "aside_price": null,
    "image": "https://m.media-amazon.com/images/I/71FGys0BbTL._AC_UF226,226_FMjpg_.jpg",
    "label": "スマートウォッチ 【1.7インチ大画面】 Bluetooth 活動量計 腕時計 スポーツウォッチ 多種類運動モード 着信通知 SMS/Twitter/Line通知 音楽再生 歩数計 遠隔カメラ 防水 睡眠データー 目覚まし時計 腕上げ点灯/天気予報/懐中電灯 iPhone&Android対応; ",
    "textContent": "￥13,498以下セール￥13,498以下セールスマートウォッチ 【1.7インチ大画面】 Bluetooth 活動量計 腕時計 スポーツウォッチ 多種類運動モード 着信通知 SMS/Twitter/Line通知 音楽再生 歩数計 遠隔カメラ 防水 睡眠データー 目覚まし時計 腕上げ点灯/天気予報/懐中電灯 iPhone&Android対応"
  },
  {
    "href": "https://www.amazon.co.jp/%E3%80%902022%E9%80%B2%E5%8C%96%E7%89%88%E3%80%91Smart-%E3%82%B9%E3%83%9E%E3%83%BC%E3%83%88%E3%82%A6%E3%82%A9%E3%83%83%E3%83%81-1-69%E3%82%A4%E3%83%B3%E3%83%81%E5%A4%A7%E7%94%BB%E9%9D%A2-%E3%82%B9%E3%83%88%E3%83%83%E3%83%97%E3%82%A6%E3%82%A9%E3%83%83%E3%83%81-%E9%9F%B3%E6%A5%BD%E3%82%B3%E3%83%B3%E3%83%88%E3%83%AD%E3%83%BC%E3%83%AB/dp/B09Y5G12FP?ref=dlx_deals_gd_dcl_img_19_066c00a7_dt_sl15_7f&tag=tokkajohotsu-22",
    "date": "2022-11-18-0229",
    "asin": "B09Y5G12FP",
    "price": null,
    "aside_price": null,
    "image": "https://m.media-amazon.com/images/I/51g7+EWxtUS._AC_UF226,226_FMjpg_.jpg",
    "label": "【2022進化版】Smart watch スマートウォッチ 腕時計 活動量計 歩数計 万歩計 1.69インチ大画面 DIY 多種文字盤 多機能 睡眠モニター GPS 消費カロリー 多運動モード ストップウォッチ 目覚まし時計 自由設定 天気予報 音楽再生 音楽コントロール 遠隔撮影 スマホ探し 腕上げ点灯 座りすぎ通知 防水性強い ins/Line/Twitter/Eメール/着信通知 各種対応 日本語説明書; ",
    "textContent": "最大68%OFFセール最大68%OFFセール【2022進化版】Smart watch スマートウォッチ 腕時計 活動量計 歩数計 万歩計 1.69インチ大画面 DIY 多種文字盤 多機能 睡眠モニター GPS 消費カロリー 多運動モード ストップウォッチ 目覚まし時計 自由設定 天気予報 音楽再生 音楽コントロール 遠隔撮影 スマホ探し 腕上げ点灯 座りすぎ通知 防水性強い ins/Line/Twitter/Eメール/着信通知 各種対応 日本語説明書"
  },
  {
    "href": "https://www.amazon.co.jp/%E3%82%AD%E3%83%BC%E3%82%B1%E3%83%BC%E3%82%B9-%E3%82%B9%E3%83%9E%E3%83%BC%E3%83%88%E3%82%AD%E3%83%BC%E3%82%B1%E3%83%BC%E3%82%B9-%E3%83%A1%E3%83%B3%E3%82%BA-%E3%82%AB%E3%83%BC%E3%83%89%E3%82%AD%E3%83%BC%E3%82%B1%E3%83%BC%E3%82%B9-%E8%BB%8A%E3%82%AD%E3%83%BC%E3%82%B1%E3%83%BC%E3%82%B9%E3%80%901005%E3%80%91/dp/B0BHSLJ2Y6?ref=dlx_deals_gd_dcl_img_20_356c4472_dt_sl15_7f&tag=tokkajohotsu-22",
    "date": "2022-11-18-0229",
    "asin": "B0BHSLJ2Y6",
    "price": null,
    "aside_price": null,
    "image": "https://m.media-amazon.com/images/I/41TtG3cb62L._AC_UF226,226_FMjpg_.jpg",
    "label": "キーケース スマートキーケース メンズ 本革 カードキーケース 車キーケース; ",
    "textContent": "最大82%OFFセール最大82%OFFセールキーケース スマートキーケース メンズ 本革 カードキーケース 車キーケース"
  },
  {
    "href": "https://www.amazon.co.jp/deal/a3f47007?showVariations=true&ref=dlx_deals_gd_dcl_img_21_a3f47007_dt_sl15_7f&tag=tokkajohotsu-22",
    "date": "2022-11-18-0229",
    "asin": null,
    "price": null,
    "aside_price": null,
    "image": "https://m.media-amazon.com/images/I/51HO63pclbL._AC_UF226,226_FMjpg_.jpg",
    "label": "アイリス 人気のテレビがお買得; ",
    "textContent": "最大9%OFFセール最大9%OFFセールアイリス 人気のテレビがお買得"
  },
  {
    "href": "https://www.amazon.co.jp/s/browse/?ie=UTF8&node=3733238051&ref=dlx_deals_gd_dcl_img_22_f269d11d_dt_sl15_7f&tag=tokkajohotsu-22",
    "date": "2022-11-18-0229",
    "asin": "3733238051",
    "price": null,
    "aside_price": null,
    "image": "https://m.media-amazon.com/images/I/41dYVMGqxCL._AC_UF226,226_FMjpg_.jpg",
    "label": "Amazon限定ブランド キリン LAKURASHI 自然が磨いた天然水 2リットル ペットボトル ミネラルウォーター × 9本; ",
    "textContent": "最大37%OFFセール最大37%OFFセールAmazon限定ブランド キリン LAKURASHI 自然が磨いた天然水 2リットル ペットボトル ミネラルウォーター × 9本"
  },
  {
    "href": "https://www.amazon.co.jp/deal/0cfa01ca?showVariations=true&ref=dlx_deals_gd_dcl_img_23_0cfa01ca_dt_sl15_7f&tag=tokkajohotsu-22",
    "date": "2022-11-18-0229",
    "asin": null,
    "price": null,
    "aside_price": null,
    "image": "https://m.media-amazon.com/images/I/51OtYgYtbzL._AC_UF226,226_FMjpg_.jpg",
    "label": "【SONYのテレビがお買い得】; ",
    "textContent": "最大33%OFFセール最大33%OFFセール【SONYのテレビがお買い得】"
  },
  {
    "href": "https://www.amazon.co.jp/deal/9d07abd6?showVariations=true&ref=dlx_deals_gd_dcl_img_24_9d07abd6_dt_sl15_7f&tag=tokkajohotsu-22",
    "date": "2022-11-18-0229",
    "asin": null,
    "price": null,
    "aside_price": null,
    "image": "https://m.media-amazon.com/images/I/31wQY35xy6L._AC_UF226,226_FMjpg_.jpg",
    "label": "【プライム会員限定】シャープの洗濯機・冷蔵庫がお買い得; ",
    "textContent": "最大22%OFFプライムで最大22%OFFプライムで【プライム会員限定】シャープの洗濯機・冷蔵庫がお買い得"
  },
  {
    "href": "https://www.amazon.co.jp/USB-Type-C-%E3%82%AF%E3%82%A2%E3%83%83%E3%83%89%E3%83%87%E3%82%A3%E3%82%B9%E3%83%97%E3%83%AC%E3%82%A4%E5%87%BA%E5%8A%9B%E5%AF%BE%E5%BF%9C-2-5G%E6%9C%89%E7%B7%9ALAN%E3%83%9D%E3%83%BC%E3%83%88%E4%BB%98%E3%81%8D%E5%B0%8F%E5%9E%8B%E3%83%91%E3%82%BD%E3%82%B3%E3%83%B3-MINISFORUM-UM560%E3%83%9F%E3%83%8B%E3%83%91%E3%82%BD%E3%82%B3%E3%83%B3/dp/B08KWJFZTZ?ref=dlx_deals_gd_dcl_img_25_141ae5f3_dt_sl15_7f&tag=tokkajohotsu-22",
    "date": "2022-11-18-0229",
    "asin": "MINISFORUM",
    "price": null,
    "aside_price": null,
    "image": "https://m.media-amazon.com/images/I/41ZarI7N7dL._AC_UF226,226_FMjpg_.jpg",
    "label": "MINISFORUM HM50ミニPC AMD Ryzen 5 4500U 6C/6T 小型PC Mini pc DDR4 16GB 256GB PCIe SSD 1000M/2500M LAN BT5.0 AMD Radeon Graphics 4kトリプルディスプレイ出力 ミニパソコン; ",
    "textContent": "最大25%OFFセール最大25%OFFセールMINISFORUM HM50ミニPC AMD Ryzen 5 4500U 6C/6T 小型PC Mini pc DDR4 16GB 256GB PCIe SSD 1000M/2500M LAN BT5.0 AMD Radeon Graphics 4kトリプルディスプレイ出力 ミニパソコン"
  },
  {
    "href": "https://www.amazon.co.jp/deal/3a9a81f6?ref=dlx_deals_gd_dcl_img_26_3a9a81f6_dt_sl15_7f&tag=tokkajohotsu-22",
    "date": "2022-11-18-0229",
    "asin": null,
    "price": null,
    "aside_price": null,
    "image": "https://m.media-amazon.com/images/I/51mgA6FRm0L._AC_UF226,226_FMjpg_.jpg",
    "label": "コカ・コーラ社 商品がお得; ",
    "textContent": "￥1,940以下セール￥1,940以下セールコカ・コーラ社 商品がお得"
  },
  {
    "href": "https://www.amazon.co.jp/Dell-%E3%83%AF%E3%82%A4%E3%83%89%E3%83%95%E3%83%AC%E3%83%BC%E3%83%A0%E3%83%AC%E3%82%B9%E3%83%A2%E3%83%8B%E3%82%BF%E3%83%BC-S2421HS-3%E5%B9%B4%E9%96%93%E7%84%A1%E8%BC%9D%E7%82%B9%E4%BA%A4%E6%8F%9B%E4%BF%9D%E8%A8%BC-FreeSync%E2%84%A2/dp/B08HGM2WZQ?ref=dlx_deals_gd_dcl_img_27_049b06a7_dt_sl15_7f&tag=tokkajohotsu-22",
    "date": "2022-11-18-0229",
    "asin": "B08HGM2WZQ",
    "price": null,
    "aside_price": null,
    "image": "https://m.media-amazon.com/images/I/51aqTh7eqgL._AC_UF226,226_FMjpg_.jpg",
    "label": "【Amazon.co.jp限定】 Dell S2421HS 23.8インチ モニター (3年間無輝点交換保証/フルHD/IPS非光沢/DP・HDMI/縦横回転・高さ調節/AMD FreeSync); ",
    "textContent": "セールセール【Amazon.co.jp限定】 Dell S2421HS 23.8インチ モニター (3年間無輝点交換保証/フルHD/IPS非光沢/DP・HDMI/縦横回転・高さ調節/AMD FreeSync)"
  },
  {
    "href": "https://www.amazon.co.jp/%E3%83%96%E3%83%AB%E3%83%BC%E3%83%88%E3%82%A5%E3%83%BC%E3%82%B9%E3%82%A4%E3%83%A4%E3%83%9B%E3%83%B31200mAh%E5%85%85%E9%9B%BB%E3%82%B1%E3%83%BC%E3%82%B9%E4%BB%98%E3%81%8D-%E3%82%A4%E3%83%A4%E3%83%95%E3%82%A9%E3%83%B3%E6%9C%AC%E4%BD%937%E6%99%82%E9%96%93%E5%86%8D%E7%94%9F-%E6%9C%80%E6%96%B0Bluetooth5-0-%E3%83%8E%E3%82%A4%E3%82%BA%E3%82%AD%E3%83%A3%E3%83%B3%E3%82%BB%E3%83%AA%E3%83%B3%E3%82%B0%E6%A9%9F%E8%83%BD-LED%E3%83%87%E3%82%A3%E3%82%B9%E3%83%97%E3%83%AC%E3%82%A4%E6%AE%8B%E9%87%8F%E8%A1%A8%E7%A4%BA/dp/B0BJZLTLMJ?ref=dlx_deals_gd_dcl_img_28_b9571c53_dt_sl15_7f&tag=tokkajohotsu-22",
    "date": "2022-11-18-0229",
    "asin": "B0BJZLTLMJ",
    "price": null,
    "aside_price": null,
    "image": "https://m.media-amazon.com/images/I/51xGFPYbeiL._AC_UF226,226_FMjpg_.jpg",
    "label": "【2022新登場】Bluetooth イヤホン ワイヤレスイヤホン ブルートゥースイヤホン イヤフォン単体6時間再生 合計200時間再生 1200mAh充電ケース付 Bluetooth 5.0+EDR搭載 Hi-Fi重低音 自動ペアリング IPX7防水 LEDディスプレイ残量表示 ハンズフリー通話 CVC8.0ノイズキャンセリング機能 左右分離型 快適なフィット感 音量調整可能 小型/軽量 (ブラック); ",
    "textContent": "最大66%OFFセール最大66%OFFセール【2022新登場】Bluetooth イヤホン ワイヤレスイヤホン ブルートゥースイヤホン イヤフォン単体6時間再生 合計200時間再生 1200mAh充電ケース付 Bluetooth 5.0+EDR搭載 Hi-Fi重低音 自動ペアリング IPX7防水 LEDディスプレイ残量表示 ハンズフリー通話 CVC8.0ノイズキャンセリング機能 左右分離型 快適なフィット感 音量調整可能 小型/軽量 (ブラック)"
  },
  {
    "href": "https://www.amazon.co.jp/GTRacing-%E3%82%B2%E3%83%BC%E3%83%9F%E3%83%B3%E3%82%B0%E3%83%81%E3%82%A7%E3%82%A2-%E3%82%AA%E3%83%83%E3%83%88%E3%83%9E%E3%83%B3%E4%BB%98%E3%81%8D-%E3%82%BD%E3%83%95%E3%82%A1%E3%83%BC%E3%81%AE%E5%BA%A7%E3%82%8A%E5%BF%83%E5%9C%B0-%E9%9D%9E%E5%86%8D%E7%94%9F%E3%82%A6%E3%83%AC%E3%82%BF%E3%83%B3%E6%8E%A1%E7%94%A8/dp/B09VC3BC6V?ref=dlx_deals_gd_dcl_img_29_04ed3af1_dt_sl15_7f&tag=tokkajohotsu-22",
    "date": "2022-11-18-0229",
    "asin": "B09VC3BC6V",
    "price": null,
    "aside_price": null,
    "image": "https://m.media-amazon.com/images/I/41+r8HpunIL._AC_UF226,226_FMjpg_.jpg",
    "label": "GTRacing ゲーミングチェア ファブリック オットマン付き オフィスチェア デスクチェア ゲーム用チェア リクライニング 通気性 ソファーの座り心地 非再生ウレタン採用 (White, オットマンなし); ",
    "textContent": "最大28%OFFセール最大28%OFFセールGTRacing ゲーミングチェア ファブリック オットマン付き オフィスチェア デスクチェア ゲーム用チェア リクライニング 通気性 ソファーの座り心地 非再生ウレタン採用 (White, オットマンなし)"
  },
  {
    "href": "https://www.amazon.co.jp/deal/a2c21f40?showVariations=true&ref=dlx_deals_gd_dcl_img_30_a2c21f40_dt_sl15_7f&tag=tokkajohotsu-22",
    "date": "2022-11-18-0229",
    "asin": null,
    "price": null,
    "aside_price": null,
    "image": "https://m.media-amazon.com/images/I/31aN2An9O2L._AC_UF226,226_FMjpg_.jpg",
    "label": "TP-Linkのルーター・スマートホーム機器がセールでお得; ",
    "textContent": "最大23%OFFセール最大23%OFFセールTP-Linkのルーター・スマートホーム機器がセールでお得"
  },
  {
    "href": "https://www.amazon.co.jp/%E3%83%8F%E3%82%A4%E3%82%BB%E3%83%B3%E3%82%B9-ULED%E6%B6%B2%E6%99%B6%E3%83%86%E3%83%AC%E3%83%93-65U8F-4K%E3%83%81%E3%83%A5%E3%83%BC%E3%83%8A%E3%83%BC%E5%86%85%E8%94%B5-2020%E5%B9%B4%E3%83%A2%E3%83%87%E3%83%AB/dp/B087Q5VX1X?ref=dlx_deals_gd_dcl_img_31_8e0b338b_dt_sl15_7f&tag=tokkajohotsu-22",
    "date": "2022-11-18-0229",
    "asin": "B087Q5VX1X",
    "price": null,
    "aside_price": null,
    "image": "https://m.media-amazon.com/images/I/51uGvRHn-8L._AC_UF226,226_FMjpg_.jpg",
    "label": "【お買い得】ハイセンス 65型 4Kチューナー内蔵 ULED 液晶 テレビ 65U8F; ",
    "textContent": "15%OFFセール15%OFFセール【お買い得】ハイセンス 65型 4Kチューナー内蔵 ULED 液晶 テレビ 65U8F"
  },
  {
    "href": "https://www.amazon.co.jp/deal/10199993?showVariations=true&ref=dlx_deals_gd_dcl_img_32_10199993_dt_sl15_7f&tag=tokkajohotsu-22",
    "date": "2022-11-18-0229",
    "asin": null,
    "price": null,
    "aside_price": null,
    "image": "https://m.media-amazon.com/images/I/51z5In9PfKL._AC_UF226,226_FMjpg_.jpg",
    "label": "LG商品がお買い得; ",
    "textContent": "最大37%OFFセール最大37%OFFセールLG商品がお買い得"
  },
  {
    "href": "https://www.amazon.co.jp/Jackery-%E3%83%9D%E3%83%BC%E3%82%BF%E3%83%96%E3%83%AB%E9%9B%BB%E6%BA%90-708-%E3%83%9D%E3%83%BC%E3%82%BF%E3%83%96%E3%83%AB%E3%83%90%E3%83%83%E3%83%86%E3%83%AA%E3%83%BC-MPPT%E5%88%B6%E5%BE%A1%E6%96%B9%E5%BC%8F%E6%8E%A1%E7%94%A8/dp/B093V5VJ6N?ref=dlx_deals_gd_dcl_img_33_49088aae_dt_sl15_7f&tag=tokkajohotsu-22",
    "date": "2022-11-18-0229",
    "asin": "B093V5VJ6N",
    "price": null,
    "aside_price": null,
    "image": "https://m.media-amazon.com/images/I/51C8wilfKXS._AC_UF226,226_FMjpg_.jpg",
    "label": "Jackery ポータブル電源 708 ポータブルバッテリー 大容量 191400mAh/708Wh 家庭用 アウトドア用 バックアップ電源 PSE認証済 純正弦波 MPPT制御方式採用 AC/DC/USB出力 四つの充電方法 液晶大画面表示 車中泊 キャンプ 防災 非常用電源 発電機 ジャクリ 708; ",
    "textContent": "35%OFFセール35%OFFセールJackery ポータブル電源 708 ポータブルバッテリー 大容量 191400mAh/708Wh 家庭用 アウトドア用 バックアップ電源 PSE認証済 純正弦波 MPPT制御方式採用 AC/DC/USB出力 四つの充電方法 液晶大画面表示 車中泊 キャンプ 防災 非常用電源 発電機 ジャクリ 708"
  },
  {
    "href": "https://www.amazon.co.jp/deal/9f60a0fb?showVariations=true&ref=dlx_deals_gd_dcl_img_34_9f60a0fb_dt_sl15_7f&tag=tokkajohotsu-22",
    "date": "2022-11-18-0229",
    "asin": null,
    "price": null,
    "aside_price": null,
    "image": "https://m.media-amazon.com/images/I/31a7ABLp8NL._AC_UF226,226_FMjpg_.jpg",
    "label": "西川の寝具がお買い得; ",
    "textContent": "最大11%OFFセール最大11%OFFセール西川の寝具がお買い得"
  },
  {
    "href": "https://www.amazon.co.jp/%E3%82%A4%E3%83%B3%E3%82%BD%E3%83%BC%E3%83%AB-%E4%BA%BA%E4%BD%93%E5%B7%A5%E5%AD%A6%E3%81%AB%E5%9F%BA%E3%81%A5%E3%81%84%E3%81%9F-3D%E3%82%A2%E3%83%BC%E3%83%81%E3%82%B5%E3%83%9D%E3%83%BC%E3%83%88-%E3%82%BD%E3%83%95%E3%83%88%E3%82%AF%E3%83%83%E3%82%B7%E3%83%A7%E3%83%B3-%E7%99%BB%E5%B1%B1%E3%81%AB%E9%81%A9%E7%94%A8%EF%BC%8824%EF%BD%9E27-5CM%EF%BC%89/dp/B09NDGBQ5P?ref=dlx_deals_gd_dcl_img_35_2233a3a1_dt_sl15_7f&tag=tokkajohotsu-22",
    "date": "2022-11-18-0229",
    "asin": "B09NDGBQ5P",
    "price": null,
    "aside_price": null,
    "image": "https://m.media-amazon.com/images/I/41xsokl41BL._AC_UF226,226_FMjpg_.jpg",
    "label": "インソール 人体工学に基づいた インソール 036; ",
    "textContent": "最大74%OFFセール最大74%OFFセールインソール 人体工学に基づいた インソール 036"
  },
  {
    "href": "https://www.amazon.co.jp/deal/303c18d2?showVariations=true&ref=dlx_deals_gd_dcl_img_36_303c18d2_dt_sl15_7f&tag=tokkajohotsu-22",
    "date": "2022-11-18-0229",
    "asin": null,
    "price": null,
    "aside_price": null,
    "image": "https://m.media-amazon.com/images/I/51cRGbYtnqS.._AC_UF226,226_FMjpg_.jpg",
    "label": "【Amazon.co.jp限定カラー】シモンズがお買い得; ",
    "textContent": "最大5%OFFセール最大5%OFFセール【Amazon.co.jp限定カラー】シモンズがお買い得"
  },
  {
    "href": "https://www.amazon.co.jp/%E3%82%AF%E3%82%A4%E3%83%BC%E3%83%B3%EF%BC%88195%C3%97160%C3%9723cm%EF%BC%89-%E7%8B%AC%E8%87%AA%E9%96%8B%E7%99%BA%E3%82%A6%E3%83%AC%E3%82%BF%E3%83%B3%E3%83%95%E3%82%A9%E3%83%BC%E3%83%A03%E5%B1%A4%E6%A7%8B%E9%80%A0-%E5%AF%9D%E5%A7%BF%E5%8B%A2%E3%83%BB%E5%AF%9D%E8%BF%94%E3%82%8A%E3%82%B5%E3%83%9D%E3%83%BC%E3%83%88-%E3%83%9E%E3%83%83%E3%83%88%E3%83%AC%E3%82%B9%E6%BB%91%E3%82%8A%E9%98%B2%E6%AD%A2%E6%8A%80%E8%A1%93-120%E6%97%A5%E9%96%93%E8%BF%94%E5%93%81%E3%83%BB%E8%BF%94%E9%87%91%E5%8F%AF%E8%83%BD/dp/B09KVKZGS6?ref=dlx_deals_gd_dcl_img_37_fa953c49_dt_sl15_7f&tag=tokkajohotsu-22",
    "date": "2022-11-18-0229",
    "asin": "B09KVKZGS6",
    "price": null,
    "aside_price": null,
    "image": "https://m.media-amazon.com/images/I/318U47xlQ0L._AC_UF226,226_FMjpg_.jpg",
    "label": "【NEWコアラマットレス】硬さ寝ごこち調整可 振動吸収 防菌防カビ 通気性 圧縮配送 快眠 返品可能 10年保証 [日本専用仕様]; ",
    "textContent": "20%OFFセール20%OFFセール【NEWコアラマットレス】硬さ寝ごこち調整可 振動吸収 防菌防カビ 通気性 圧縮配送 快眠 返品可能 10年保証 [日本専用仕様]"
  },
  {
    "href": "https://www.amazon.co.jp/deal/5f1d93ba?showVariations=true&ref=dlx_deals_gd_dcl_img_38_5f1d93ba_dt_sl15_7f&tag=tokkajohotsu-22",
    "date": "2022-11-18-0229",
    "asin": null,
    "price": null,
    "aside_price": null,
    "image": "https://m.media-amazon.com/images/I/41zdRqB4DxL._AC_UF226,226_FMjpg_.jpg",
    "label": "おすすめのブラウンの理美容家電がお買い得; ",
    "textContent": "最大15%OFFセール最大15%OFFセールおすすめのブラウンの理美容家電がお買い得"
  },
  {
    "href": "https://www.amazon.co.jp/%E3%80%902020%E9%80%B2%E5%8C%96%E7%89%88%E3%80%91%E3%83%A8%E3%82%AC%E3%83%9E%E3%83%83%E3%83%88-%E3%83%88%E3%83%AC%E3%83%BC%E3%83%8B%E3%83%B3%E3%82%B0%E3%83%9E%E3%83%83%E3%83%88-%E3%83%94%E3%83%A9%E3%83%86%E3%82%A3%E3%82%B9%E3%83%9E%E3%83%83%E3%83%88-%E3%82%A8%E3%82%AF%E3%82%B5%E3%82%B5%E3%82%A4%E3%82%BA%E3%83%9E%E3%83%83%E3%83%88-%E3%82%AF%E3%83%83%E3%82%B7%E3%83%A7%E3%83%B3%E6%80%A7%E6%8A%9C%E7%BE%A4/dp/B08C2WXT21?ref=dlx_deals_gd_dcl_img_39_b00819bc_dt_sl15_7f&tag=tokkajohotsu-22",
    "date": "2022-11-18-0229",
    "asin": "B08C2WXT21",
    "price": null,
    "aside_price": null,
    "image": "https://m.media-amazon.com/images/I/51R7Mir0mvL._AC_UF226,226_FMjpg_.jpg",
    "label": "ヨガマット トレーニングマット ピラティスマット エクササイズマット 厚め NBR素材 高密度 厚さ10mm 初心者に優しい 床の保護 防音対策 ピラティス ストレッチ 体幹トレーニング 筋トレ フィットネス 持ち運び 収納簡単 水洗い可能 男女兼用 収納ケース付 yoga mat; ",
    "textContent": "21%OFFセール21%OFFセールヨガマット トレーニングマット ピラティスマット エクササイズマット 厚め NBR素材 高密度 厚さ10mm 初心者に優しい 床の保護 防音対策 ピラティス ストレッチ 体幹トレーニング 筋トレ フィットネス 持ち運び 収納簡単 水洗い可能 男女兼用 収納ケース付 yoga mat"
  },
  {
    "href": "https://www.amazon.co.jp/%E3%83%88%E3%83%AA%E3%83%BC%E3%83%88%E3%83%A1%E3%83%B3%E3%83%88-%E5%A4%A9%E7%84%B6%E7%94%B1%E6%9D%A5%E6%B4%97%E6%B5%84-%E3%83%8E%E3%83%B3%E3%82%B7%E3%83%AA%E3%82%B3%E3%83%B3%E3%82%B7%E3%83%A3%E3%83%B3%E3%83%97%E3%83%BC-%E3%83%93%E3%82%BF%E3%83%9F%E3%83%B3C%E8%AA%98%E5%B0%8E%E4%BD%93-%E3%83%A2%E3%82%A4%E3%82%B9%E3%83%81%E3%83%A3%E3%83%BC%E3%82%BB%E3%83%83%E3%83%88/dp/B07XVCPVC7?ref=dlx_deals_gd_dcl_img_40_245ea64a_dt_sl15_7f&tag=tokkajohotsu-22",
    "date": "2022-11-18-0229",
    "asin": "B07XVCPVC7",
    "price": null,
    "aside_price": null,
    "image": "https://m.media-amazon.com/images/I/41GQH0J4dwS._AC_UF226,226_FMjpg_.jpg",
    "label": "オルナ オーガニック シャンプー トリートメント セット 各500ml 無添加 日本製; ",
    "textContent": "最大37%OFFセール最大37%OFFセールオルナ オーガニック シャンプー トリートメント セット 各500ml 無添加 日本製"
  },
  {
    "href": "https://www.amazon.co.jp/deal/242d355a?showVariations=true&ref=dlx_deals_gd_dcl_img_41_242d355a_dt_sl15_7f&tag=tokkajohotsu-22",
    "date": "2022-11-18-0229",
    "asin": null,
    "price": null,
    "aside_price": null,
    "image": "https://m.media-amazon.com/images/I/61gMeMFM8LL._AC_UF226,226_FMjpg_.jpg",
    "label": "カゴメ飲料がお買い得; ",
    "textContent": "最大31%OFFセール最大31%OFFセールカゴメ飲料がお買い得"
  },
  {
    "href": "https://www.amazon.co.jp/%E3%80%90%E6%96%B0%E4%B8%96%E4%BB%A3%E3%83%AF%E3%82%A4%E3%83%A4%E3%83%AC%E3%82%B9%E3%83%BB%E8%93%8B%E3%82%92%E9%96%8B%E3%81%91%E3%81%9F%E3%82%89%E7%9E%AC%E6%99%82%E6%8E%A5%E7%B6%9A%E3%80%91bluetooth-%E5%A4%A7%E5%AE%B9%E9%87%8F2600mAh%E5%85%85%E9%9B%BB%E3%82%B1%E3%83%BC%E3%82%B9-Bluetooth%E3%83%98%E3%83%83%E3%83%89%E3%82%BB%E3%83%83%E3%83%88-%E3%83%A9%E3%83%B3%E3%83%8B%E3%83%B3%E3%82%B0%E3%82%84%E3%82%B9%E3%83%9D%E3%83%BC%E3%83%84%E3%81%AA%E3%81%A9%E3%81%AB%E9%81%A9%E7%94%A8-%E6%97%A5%E6%9C%AC%E8%AA%9E%E5%8F%96%E6%89%B1%E8%AA%AC%E6%98%8E%E6%9B%B8%EF%BC%88%E3%83%96%E3%83%A9%E3%83%83%E3%82%AF%EF%BC%89/dp/B0B8S4JDPZ?ref=dlx_deals_gd_dcl_img_42_8894c5a0_dt_sl15_7f&tag=tokkajohotsu-22",
    "date": "2022-11-18-0229",
    "asin": "B0B8S4JDPZ",
    "price": null,
    "aside_price": null,
    "image": "https://m.media-amazon.com/images/I/41vs3HodToL._AC_UF226,226_FMjpg_.jpg",
    "label": "【新世代ワイヤレス・蓋を開けたら瞬時接続】bluetooth イヤホン Bluetooth5.3+EDR ワイヤレスイヤホン AAC/ SBCに対応 ハイレゾ音質 大容量2600mAh充電ケース イヤフォン単体8時間再生 合計150時間連続再生 自動ペアリング LEDディスプレイ残量表示 タッチコントロール 簡単操作 HiFi重低音 ハンズフリー通話 Type-C急速充電 ENCノイズキャンセリング 小型/軽量 完全ワイヤレス イヤホン IPX7防水 心地よい装着感 左右分離型 片耳/両耳モード ブルートゥースイヤホン Bluetoothヘッドセット ビジネス/WEB会議/テレワーク/仕事/勉強/通勤/通学/ランニングやスポーツなどに適用 日本語取扱説明書（ブラック）; ",
    "textContent": "26%OFFセール26%OFFセール【新世代ワイヤレス・蓋を開けたら瞬時接続】bluetooth イヤホン Bluetooth5.3+EDR ワイヤレスイヤホン AAC/ SBCに対応 ハイレゾ音質 大容量2600mAh充電ケース イヤフォン単体8時間再生 合計150時間連続再生 自動ペアリング LEDディスプレイ残量表示 タッチコントロール 簡単操作 HiFi重低音 ハンズフリー通話 Type-C急速充電 ENCノイズキャンセリング 小型/軽量 完全ワイヤレス イヤホン IPX7防水 心地よい装着感 左右分離型 片耳/両耳モード ブルートゥースイヤホン Bluetoothヘッドセット ビジネス/WEB会議/テレワーク/仕事/勉強/通勤/通学/ランニングやスポーツなどに適用 日本語取扱説明書（ブラック）88%カートに追加済み"
  },
  {
    "href": "https://www.amazon.co.jp/GTRACING-GT890MF-RED-VC-%E3%82%B2%E3%83%BC%E3%83%9F%E3%83%B3%E3%82%B0%E3%83%81%E3%82%A7%E3%82%A2/dp/B07QGY4VGK?ref=dlx_deals_gd_dcl_img_43_506c064a_dt_sl15_7f&tag=tokkajohotsu-22",
    "date": "2022-11-18-0229",
    "asin": "B07QGY4VGK",
    "price": null,
    "aside_price": null,
    "image": "https://m.media-amazon.com/images/I/41FfuQdnHBL._AC_UF226,226_FMjpg_.jpg",
    "label": "GTRACING ゲーミングチェア スピーカー付き オットマン ゲーミングスピーカー付き サラウンド効果 オフィスチェア フットレスト デスクチェア ゲーム用チェア リクライニング パソコンチェア ハイバック ヘッドレスト ランバーサポート ひじ掛け付き PUレザー PC/PS4/PS5/XBOX/SWITCH等対応(専用USBアダプタ使用) GT890MF-RED; ",
    "textContent": "最大31%OFFセール最大31%OFFセールGTRACING ゲーミングチェア スピーカー付き オットマン ゲーミングスピーカー付き サラウンド効果 オフィスチェア フットレスト デスクチェア ゲーム用チェア リクライニング パソコンチェア ハイバック ヘッドレスト ランバーサポート ひじ掛け付き PUレザー PC/PS4/PS5/XBOX/SWITCH等対応(専用USBアダプタ使用) GT890MF-RED"
  },
  {
    "href": "https://www.amazon.co.jp/deal/d6d7fdfe?showVariations=true&ref=dlx_deals_gd_dcl_img_44_d6d7fdfe_dt_sl15_7f&tag=tokkajohotsu-22",
    "date": "2022-11-18-0229",
    "asin": null,
    "price": null,
    "aside_price": null,
    "image": "https://m.media-amazon.com/images/I/218Z35VQAJL._AC_UF226,226_FMjpg_.jpg",
    "label": "おすすめのフィリップスの理美容家電がお買い得; ",
    "textContent": "最大31%OFFセール最大31%OFFセールおすすめのフィリップスの理美容家電がお買い得"
  },
  {
    "href": "https://www.amazon.co.jp/NINJOR-GOLF-%E3%83%8B%E3%83%B3%E3%82%B8%E3%83%A3%E3%83%BC%E3%82%B4%E3%83%AB%E3%83%95%EF%BC%89%E3%82%B4%E3%83%AB%E3%83%95-%E5%9E%8B%E7%95%AANJ007-%E3%83%AC%E3%83%BC%E3%82%B6%E3%83%BC%E6%B3%A2%E9%95%B7%EF%BC%9AClass/dp/B0B1P8YCRH?ref=dlx_deals_gd_dcl_img_45_cfa95484_dt_sl15_7f&tag=tokkajohotsu-22",
    "date": "2022-11-18-0229",
    "asin": "B0B1P8YCRH",
    "price": null,
    "aside_price": null,
    "image": "https://m.media-amazon.com/images/I/41PGpqQG8RL._AC_UF226,226_FMjpg_.jpg",
    "label": "NINJOR GOLF(ニンジャーゴルフ）ゴルフ レーザー 距離計 高低差補正 防水機能 0.1秒計測 ピンサーチ 型番NJ007 レーザー波長：Class I laser 距離測定器 距離計測器; ",
    "textContent": "15%OFFセール15%OFFセールNINJOR GOLF(ニンジャーゴルフ）ゴルフ レーザー 距離計 高低差補正 防水機能 0.1秒計測 ピンサーチ 型番NJ007 レーザー波長：Class I laser 距離測定器 距離計測器"
  },
  {
    "href": "https://www.amazon.co.jp/Beelink-ser4%E3%83%9F%E3%83%8BPC-Windows-8%E3%82%B3%E3%82%A2%EF%BC%88%E6%9C%80%E5%A4%A74-1GHz%EF%BC%8916GB-SSD%E3%82%92%E3%82%B5%E3%83%9D%E3%83%BC%E3%83%88/dp/B0B4NGHRFP?ref=dlx_deals_gd_dcl_img_46_0b0f0d46_dt_sl15_7f&tag=tokkajohotsu-22",
    "date": "2022-11-18-0229",
    "asin": "B0B4NGHRFP",
    "price": null,
    "aside_price": null,
    "image": "https://m.media-amazon.com/images/I/51YfIDydSnL._AC_UF226,226_FMjpg_.jpg",
    "label": "Beelink SER5ミニPC Windows 11 Pro AMD Ryzen 5 5560U 6コア12スレッド（2.3~4GHz）16GB RAM 500GB NVME SSD/WiFi 6E /BT Type-C(4K@60Hz) / 2*HDMI 4K@60Hz,2.5\"HDD/SSDをサポート; ",
    "textContent": "最大31%OFFセール最大31%OFFセールBeelink SER5ミニPC Windows 11 Pro AMD Ryzen 5 5560U 6コア12スレッド（2.3~4GHz）16GB RAM 500GB NVME SSD/WiFi 6E /BT Type-C(4K@60Hz) / 2*HDMI 4K@60Hz,2.5\"HDD/SSDをサポート"
  },
  {
    "href": "https://www.amazon.co.jp/%E3%82%B2%E3%83%BC%E3%83%9F%E3%83%B3%E3%82%B0%E3%83%81%E3%82%A7%E3%82%A2-%E3%82%AA%E3%83%95%E3%82%A3%E3%82%B9%E3%83%81%E3%82%A7%E3%82%A2-%E3%82%B2%E3%83%BC%E3%83%A0%E7%94%A8%E3%83%81%E3%82%A7%E3%82%A2-%E3%83%87%E3%82%B9%E3%82%AF%E3%83%81%E3%82%A7%E3%82%A2-%E3%83%91%E3%82%BD%E3%82%B3%E3%83%B3%E3%83%81%E3%82%A7%E3%82%A2-%EF%BC%91%EF%BC%96%EF%BC%95%E5%BA%A6%E3%83%AA%E3%82%AF%E3%83%A9%E3%82%A4%E3%83%8B%E3%83%B3%E3%82%B0%E6%A9%9F%E8%83%BD/dp/B09CTRHVQ2?ref=dlx_deals_gd_dcl_img_47_db428719_dt_sl15_7f&tag=tokkajohotsu-22",
    "date": "2022-11-18-0229",
    "asin": "B09CTRHVQ2",
    "price": null,
    "aside_price": null,
    "image": "https://m.media-amazon.com/images/I/41Tr6zRJFNL._AC_UF226,226_FMjpg_.jpg",
    "label": "GXTRACE ゲーミングチェア オフィスチェア ゲーム用チェア デスクチェア パソコンチェア オットマン付き 人間工学 １６５度リクライニング機能 ハイバック テレワーク椅子 PCチェア (White); ",
    "textContent": "最大32%OFFセール最大32%OFFセールGXTRACE ゲーミングチェア オフィスチェア ゲーム用チェア デスクチェア パソコンチェア オットマン付き 人間工学 １６５度リクライニング機能 ハイバック テレワーク椅子 PCチェア (White)"
  },
  {
    "href": "https://www.amazon.co.jp/deal/72061636?showVariations=true&ref=dlx_deals_gd_dcl_img_48_72061636_dt_sl15_7f&tag=tokkajohotsu-22",
    "date": "2022-11-18-0229",
    "asin": null,
    "price": null,
    "aside_price": null,
    "image": "https://m.media-amazon.com/images/I/41dZUivSFpL._AC_UF226,226_FMjpg_.jpg",
    "label": "Adobe クリエイティブソフトタイムセール; ",
    "textContent": "34%OFFセール34%OFFセールAdobe クリエイティブソフトタイムセール"
  },
  {
    "href": "https://www.amazon.co.jp/TECLAST-1TB%E6%8B%A1%E5%BC%B5%E5%8F%AF%E8%83%BD%E3%80%811-8Ghz-4%E3%82%B3%E3%82%A2CPU%E3%80%81%E8%A7%A3%E5%83%8F%E5%BA%A61280%C3%97800IPS%E3%80%81WiFi%E3%83%A2%E3%83%87%E3%83%AB%E3%82%BF%E3%83%96%E3%83%AC%E3%83%83%E3%83%8810%E3%82%A4%E3%83%B3%E3%83%81%E3%80%81Google-5000mAh%E3%80%81%E3%83%87%E3%83%A5%E3%82%A2%E3%83%AB%E3%82%AB%E3%83%A1%E3%83%A9-OTG%E8%BB%A2%E9%80%81%E3%82%92%E3%82%B5%E3%83%9D%E3%83%BC%E3%83%88%E3%81%99%E3%82%8B%E3%80%81%E5%AD%90%E4%BE%9B%E3%81%AB%E3%82%82%E9%81%A9%E5%BD%93%E8%B4%88%E3%82%8A%E7%89%A9/dp/B0BGL8VYPT?ref=dlx_deals_gd_dcl_img_49_50671e50_dt_sl15_7f&tag=tokkajohotsu-22",
    "date": "2022-11-18-0229",
    "asin": "B0BGL8VYPT",
    "price": null,
    "aside_price": null,
    "image": "https://m.media-amazon.com/images/I/41zKCY+bMCL._AC_UF226,226_FMjpg_.jpg",
    "label": "Android 12 タブレット TECLAST P25Tタブレット 10イン、Android タブレット Wi-Fi 6 モデル、RAM 3GB+ROM 64GB+1TB拡張可能、1.8Ghz 4コアCPU、解像度1280×800IPS、WiFiモデルタブレット10インチ、Google GMS認証+Type-C+Bluetooth 5.0+2.4G/5G WiFi+5000mAh、デュアルカメラ+日本語取扱説明書付き+一年保証+OTG転送をサポートする、子供にも適当贈り物 [SIM対応しない]; ",
    "textContent": "15%OFFセール15%OFFセールAndroid 12 タブレット TECLAST P25Tタブレット 10イン、Android タブレット Wi-Fi 6 モデル、RAM 3GB+ROM 64GB+1TB拡張可能、1.8Ghz 4コアCPU、解像度1280×800IPS、WiFiモデルタブレット10インチ、Google GMS認証+Type-C+Bluetooth 5.0+2.4G/5G WiFi+5000mAh、デュアルカメラ+日本語取扱説明書付き+一年保証+OTG転送をサポートする、子供にも適当贈り物 [SIM対応しない]"
  },
  {
    "href": "https://www.amazon.co.jp/%E3%80%902022%E6%A5%AD%E7%95%8C%E6%96%B0%E3%83%A2%E3%83%87%E3%83%AB-Bluetooth5-3%E3%80%91-%E3%83%AF%E3%82%A4%E3%83%A4%E3%83%AC%E3%82%B9%E3%82%A4%E3%83%A4%E3%83%9B%E3%83%B3-%E3%83%93%E3%82%B8%E3%83%8D%E3%82%B9%E9%80%9A%E8%A9%B1%E3%83%BBWEB%E4%BC%9A%E8%AD%B0%E3%83%BB%E3%82%B9%E3%83%9D%E3%83%BC%E3%83%84%E3%83%BB%E9%80%9A%E5%8B%A4%E3%83%BB%E9%80%9A%E5%AD%A6-Type-C%E6%80%A5%E9%80%9F%E5%85%85%E9%9B%BB/dp/B0BJ874VNX?ref=dlx_deals_gd_dcl_img_50_6c1a9650_dt_sl15_7f&tag=tokkajohotsu-22",
    "date": "2022-11-18-0229",
    "asin": "B0BJ874VNX",
    "price": null,
    "aside_price": null,
    "image": "https://m.media-amazon.com/images/I/31RRTbk-hjL._AC_UF226,226_FMjpg_.jpg",
    "label": "【2022業界新モデル Bluetooth5.3】 ワイヤレスイヤホン 完全ワイヤレス イヤホン ENC+CVC8.0ノイ ズキャンセル 低遅延モード Hi-fi高音質 低音重視 自動ペアリング 瞬時接続 長時間再生 軽量 片耳/両耳 音量調整 快適なフィット感 Siri対応 ハンズフリー通話 ビジネス通話・WEB会議・スポーツ・通勤・通学 Type-C急速充電 iOS/Android対応 (ホワイト); ",
    "textContent": "76%OFFセール76%OFFセール【2022業界新モデル Bluetooth5.3】 ワイヤレスイヤホン 完全ワイヤレス イヤホン ENC+CVC8.0ノイ ズキャンセル 低遅延モード Hi-fi高音質 低音重視 自動ペアリング 瞬時接続 長時間再生 軽量 片耳/両耳 音量調整 快適なフィット感 Siri対応 ハンズフリー通話 ビジネス通話・WEB会議・スポーツ・通勤・通学 Type-C急速充電 iOS/Android対応 (ホワイト)55%カートに追加済み"
  },
  {
    "href": "https://www.amazon.co.jp/%E3%80%90%E4%BB%A4%E5%92%8C%E6%AC%A1%E4%B8%96%E4%BB%A3Bluetooth-Bluetooth5-3-ENC%E3%83%8E%E3%82%A4%E3%82%BA%E3%82%AD%E3%83%A3%E3%83%B3%E3%82%BB%E3%83%AA%E3%83%B3%E3%82%B0-%E3%83%96%E3%83%AB%E3%83%BC%E3%83%88%E3%82%A5%E3%83%BC%E3%82%B9%E3%82%A4%E3%83%A4%E3%83%9B%E3%83%B3-%E6%9C%80%E5%A4%A730%E6%99%82%E9%96%93%E9%9F%B3%E6%A5%BD%E5%86%8D%E7%94%9F/dp/B0BJQ8T2VM?ref=dlx_deals_gd_dcl_img_51_3d4cb979_dt_sl15_7f&tag=tokkajohotsu-22",
    "date": "2022-11-18-0229",
    "asin": "B0BJQ8T2VM",
    "price": null,
    "aside_price": null,
    "image": "https://m.media-amazon.com/images/I/21Tz3Qt2XgL._AC_UF226,226_FMjpg_.jpg",
    "label": "【令和次世代Bluetooth イヤホン】瞬間接続 ワイヤレスイヤホン Bluetooth5.3+EDR搭載 日本語音声 Hi-Fiステレオ ENCノイズキャンセリング 低遅延 ブルートゥースイヤホン 最大30時間音楽再生 Type‐C充電 AAC対応 イヤホン bluetooth 多機能タッチ操作 IPX7防水 完全ワイヤレス イヤホン インナーイヤー型 快適な装着感 ハンズフリー通話 マイク内蔵 片耳/両耳 左右分離型 自動ペアリング 小型・軽量 音量調整 ランニング/ゲーム/通勤通学/在宅勤務/WEB会議/zoom/skypeに適用 日本語取扱説明書付き ホワイト (X6); ",
    "textContent": "78%OFFセール78%OFFセール【令和次世代Bluetooth イヤホン】瞬間接続 ワイヤレスイヤホン Bluetooth5.3+EDR搭載 日本語音声 Hi-Fiステレオ ENCノイズキャンセリング 低遅延 ブルートゥースイヤホン 最大30時間音楽再生 Type‐C充電 AAC対応 イヤホン bluetooth 多機能タッチ操作 IPX7防水 完全ワイヤレス イヤホン インナーイヤー型 快適な装着感 ハンズフリー通話 マイク内蔵 片耳/両耳 左右分離型 自動ペアリング 小型・軽量 音量調整 ランニング/ゲーム/通勤通学/在宅勤務/WEB会議/zoom/skypeに適用 日本語取扱説明書付き ホワイト (X6)"
  },
  {
    "href": "https://www.amazon.co.jp/Bluetooth5-3%E6%8A%80%E8%A1%93-%E8%93%8B%E3%82%92%E9%96%8B%E3%81%91%E3%81%9F%E3%82%89%E6%8E%A5%E7%B6%9A%E3%80%91bluetooth-Eynew-LED%E3%83%87%E3%82%A3%E3%82%B9%E3%83%97%E3%83%AC%E3%82%A4%E8%A1%A8%E7%A4%BA-%E3%81%B6%E3%82%8B%E3%83%BC%E3%81%A8%E3%81%85%E3%83%BC%E3%81%99%E3%82%A4%E3%83%A4%E3%83%9B%E3%83%B3/dp/B0B7WVWRR6?ref=dlx_deals_gd_dcl_img_52_50607962_dt_sl15_7f&tag=tokkajohotsu-22",
    "date": "2022-11-18-0229",
    "asin": "B0B7WVWRR6",
    "price": null,
    "aside_price": null,
    "image": "https://m.media-amazon.com/images/I/41Yjx-vcayL._AC_UF226,226_FMjpg_.jpg",
    "label": "プラスワン スーツケース Advance SWIFT Frame 66L 72.0cm 4.9kg 5512-64 Lサイズ（5～7泊対応）カーボンブラック; ",
    "textContent": "65%OFFセール65%OFFセールプラスワン スーツケース Advance SWIFT Frame 66L 72.0cm 4.9kg 5512-64 Lサイズ（5～7泊対応）カーボンブラック"
  },
  {
    "href": "https://www.amazon.co.jp/Tineco-%E3%80%90%E4%BB%A4%E5%92%8C%E9%80%B2%E5%8C%96%E7%89%88%E3%80%91%E6%8E%83%E9%99%A4%E6%A9%9F-%E3%82%B9%E3%83%86%E3%82%A3%E3%83%83%E3%82%AF%E3%82%AF%E3%83%AA%E3%83%BC%E3%83%8A%E3%83%BC-FLOOR-ONE/dp/B0892DT4WD?ref=dlx_deals_gd_dcl_img_53_62c529a2_dt_sl15_7f&tag=tokkajohotsu-22",
    "date": "2022-11-18-0229",
    "asin": "B0892DT4WD",
    "price": null,
    "aside_price": null,
    "image": "https://m.media-amazon.com/images/I/31BvfRaeuyL._AC_UF226,226_FMjpg_.jpg",
    "label": "次世代型・水拭き掃除機; ",
    "textContent": "32%OFFセール32%OFFセール次世代型・水拭き掃除機"
  },
  {
    "href": "https://www.amazon.co.jp/%E8%80%B3%E3%82%92%E5%A1%9E%E3%81%8C%E3%81%AA%E3%81%84%E3%82%A4%E3%83%A4%E3%83%9B%E3%83%B3-%E9%AA%A8%E4%BC%9D%E5%B0%8E%E3%83%AF%E3%82%A4%E3%83%A4%E3%83%AC%E3%82%B9%E3%82%A4%E3%83%A4%E3%83%9B%E3%83%B3-%E3%81%B6%E3%82%8B%E3%83%BC%E3%81%A8%E3%83%BC%E3%81%99%E3%82%A4%E3%83%A4%E3%83%9B%E3%83%B3-Type-C%E6%80%A5%E9%80%9F%E5%85%85%E9%9B%BB-%E6%97%A5%E6%9C%AC%E8%AA%9E%E5%8F%96%E3%82%8A%E6%89%B1%E3%81%84%E8%AA%AC%E6%98%8E%E6%9B%B8/dp/B0BF5WN71R?ref=dlx_deals_gd_dcl_img_54_38e3e211_dt_sl15_7f&tag=tokkajohotsu-22",
    "date": "2022-11-18-0229",
    "asin": "B0BF5WN71R",
    "price": null,
    "aside_price": null,
    "image": "https://m.media-amazon.com/images/I/31ZdUma01wL._AC_UF226,226_FMjpg_.jpg",
    "label": "2022業界新登場 骨伝導イヤホン bluetooth マイク付き こつでんどう イヤホン bluetooth 防水 スポーツ イヤホン ランニング トレーニング サイクリング 耳を塞がないイヤホン 骨伝導ワイヤレスイヤホン ぶるーとーすイヤホン Type-C急速充電 8時間連続使用 骨伝導ヘッドホン 耳掛け式 骨伝導ヘッドセット 通話 リモート会議 テレワーク 在宅勤務に使用可能 日本語取り扱い説明書 プレゼント ブラック; ",
    "textContent": "75%OFFセール75%OFFセール2022業界新登場 骨伝導イヤホン bluetooth マイク付き こつでんどう イヤホン bluetooth 防水 スポーツ イヤホン ランニング トレーニング サイクリング 耳を塞がないイヤホン 骨伝導ワイヤレスイヤホン ぶるーとーすイヤホン Type-C急速充電 8時間連続使用 骨伝導ヘッドホン 耳掛け式 骨伝導ヘッドセット 通話 リモート会議 テレワーク 在宅勤務に使用可能 日本語取り扱い説明書 プレゼント ブラック"
  },
  {
    "href": "https://www.amazon.co.jp/deal/f1672af7?showVariations=true&ref=dlx_deals_gd_dcl_img_55_f1672af7_dt_sl15_7f&tag=tokkajohotsu-22",
    "date": "2022-11-18-0229",
    "asin": null,
    "price": null,
    "aside_price": null,
    "image": "https://m.media-amazon.com/images/I/412XGDAGzNL._AC_UF226,226_FMjpg_.jpg",
    "label": "ルンバがお買い得; ",
    "textContent": "最大30%OFFセール最大30%OFFセールルンバがお買い得"
  },
  {
    "href": "https://www.amazon.co.jp/AIFY-%E3%83%89%E3%83%AC%E3%83%BC%E3%83%97%E3%82%AB%E3%83%BC%E3%83%86%E3%83%B3-%E5%BD%A2%E6%85%8B%E8%A8%98%E6%86%B6%E5%8A%A0%E5%B7%A5%E6%B8%88%E3%81%BF-%E3%82%AB%E3%83%BC%E3%83%86%E3%83%B32%E6%9E%9A-%E5%B9%85100cm%C3%97%E4%B8%88135cm/dp/B08Y6PNSQD?ref=dlx_deals_gd_dcl_img_56_6264c2ed_dt_sl15_7f&tag=tokkajohotsu-22",
    "date": "2022-11-18-0229",
    "asin": "B08Y6PNSQD",
    "price": null,
    "aside_price": null,
    "image": "https://m.media-amazon.com/images/I/511Oc81wBDS._AC_UF226,226_FMjpg_.jpg",
    "label": "AIFY カーテン 1級 遮光 小窓 ドレープカーテン UVカット 形態記憶加工済み 断熱 節電対策 昼夜目隠し 保温 おしゃれ 洗える 洗濯機対応; ",
    "textContent": "最大32%OFFセール最大32%OFFセールAIFY カーテン 1級 遮光 小窓 ドレープカーテン UVカット 形態記憶加工済み 断熱 節電対策 昼夜目隠し 保温 おしゃれ 洗える 洗濯機対応"
  },
  {
    "href": "https://www.amazon.co.jp/deal/2a91bf45?searchAlias=fashion&ref=dlx_deals_gd_dcl_img_57_2a91bf45_dt_sl15_7f&tag=tokkajohotsu-22",
    "date": "2022-11-18-0229",
    "asin": null,
    "price": null,
    "aside_price": null,
    "image": "https://m.media-amazon.com/images/I/61UkvDkXX5L._AC_UF226,226_FMjpg_.png",
    "label": "アンダーアマーのスポーツウェアがお買い得; ",
    "textContent": "最大40%OFFセール最大40%OFFセールアンダーアマーのスポーツウェアがお買い得"
  },
  {
    "href": "https://www.amazon.co.jp/XUNTAO%E3%80%90%E6%96%B0%E6%98%87%E7%B4%9A-%E6%8A%98%E3%82%8A%E3%81%9F%E3%81%9F%E3%81%BF%E3%80%91%E8%93%8B%E4%BB%98%E3%81%8D-%E5%85%A8%E6%96%B9%E5%90%91%E3%81%8B%E3%82%89%E5%8F%96%E3%82%8A%E5%87%BA%E3%81%9B%E3%82%8B-%E3%82%AD%E3%83%A3%E3%82%B9%E3%82%BF%E3%83%BC%E4%BB%98%E3%81%8D-%E5%90%84%E7%A8%AE%E3%82%AB%E3%83%A9%E3%83%BC%EF%BC%88S/dp/B0B28WWNB7?ref=dlx_deals_gd_dcl_img_58_1ab033e9_dt_sl15_7f&tag=tokkajohotsu-22",
    "date": "2022-11-18-0229",
    "asin": "B0B28WWNB7",
    "price": null,
    "aside_price": null,
    "image": "https://m.media-amazon.com/images/I/51iMSbuF8TL._AC_UF226,226_FMjpg_.jpg",
    "label": "X XUNTAO【新昇級 収納ボックス 折りたたみ】蓋付き 積み重ね 全方向から取り出せる 収納ケース 衣類 布団 おもちゃ 小物 収納 折り畳み コンテナ ボックス 大型 プラスチック キャスター付き おしゃれ 組立簡単 多機能 防塵 防カビ 防湿 無臭 透明 厚み 強い耐荷重 大容量 家庭用 車用 複数のサイズ 各種カラー; ",
    "textContent": "最大15%OFFセール最大15%OFFセールX XUNTAO【新昇級 収納ボックス 折りたたみ】蓋付き 積み重ね 全方向から取り出せる 収納ケース 衣類 布団 おもちゃ 小物 収納 折り畳み コンテナ ボックス 大型 プラスチック キャスター付き おしゃれ 組立簡単 多機能 防塵 防カビ 防湿 無臭 透明 厚み 強い耐荷重 大容量 家庭用 車用 複数のサイズ 各種カラー"
  },
  {
    "href": "https://www.amazon.co.jp/s/browse/?ie=UTF8&node=3733836051&ref=dlx_deals_gd_dcl_img_59_0d906783_dt_sl15_7f&tag=tokkajohotsu-22",
    "date": "2022-11-18-0229",
    "asin": "3733836051",
    "price": null,
    "aside_price": null,
    "image": "https://m.media-amazon.com/images/I/51i2iXm6ltL._AC_UF226,226_FMjpg_.jpg",
    "label": "キリン 生茶 お茶 2L PET×9本; ",
    "textContent": "27%OFFセール27%OFFセールキリン 生茶 お茶 2L PET×9本"
  }
]